[
	{
		"id": 1,
		"name": "Sales Presentation",
		"position": {
			"x": -15,
			"y": 10,
			"z": -4.5
		},
		"cameraPosition": {
			"x": 6.85724,
			"y": 4,
			"z": -0.614593
		},
		"infos": [
			1
		]
	},
	{
		"id": 2,
		"name": "Connect feature to business value",
		"position": {
			"x": -42,
			"y": 10,
			"z": -4.5
		},
		"cameraPosition": {
			"x": -5.42844,
			"y": 3,
			"z": 0.21576
		},
		"infos": [
			2
		]
	},
	{
		"id": 3,
		"name": "Buyer Self-Discovery",
		"position": {
			"x": -42,
			"y": 10,
			"z": -4.5
		},
		"cameraPosition": {
			"x": -1.42844,
			"y": 3,
			"z": 0.21576
		},
		"infos": [
			3
		]
	},
	{
		"id": 4,
		"name": "Quality Control",
		"position": {
			"x": -69,
			"y": 10,
			"z": -4.5
		},
		"cameraPosition": {
			"x": -9.37532,
			"y": 3,
			"z": 2.91916
		},
		"infos": [
			4
		]
	},
	{
		"id": 5,
		"name": "Show and Tell",
		"position": {
			"x": -72,
			"y": -1,
			"z": 22
		},
		"cameraPosition": {
			"x": -13.37532,
			"y": 3,
			"z": 2.91916
		},
		"infos": [
			5
		]
	},
	{
		"id": 6,
		"name": "Trade Show",
		"position": {
			"x": -72,
			"y": -1,
			"z": 22
		},
		"cameraPosition": {
			"x": 6.5226,
			"y": 3.63,
			"z": 2.02661
		},
		"infos": [
			6
		]
	}
]